inet_api_client/__init__.py
inet_api_client/api_methods.py
inet_api_client/base_client.py
inet_api_client/client.py
inet_api_client/exceptions.py
inet_api_client-1.2.5.dist-info/METADATA
inet_api_client-1.2.5.dist-info/WHEEL
inet_api_client-1.2.5.dist-info/top_level.txt
inet_api_client-1.2.5.dist-info/RECORD
