Metadata-Version: 2.4
Name: inet-api-client
Version: 1.2.5
Summary: Inet API Client - 用于访问Sky Cloud平台API的Python客户端库
Home-page: https://github.com/sky-cloud/inet-api-client
Author: Bobby Sheng
Author-email: Bobby Sheng <Bobby@sky-cloud.net>
License: MIT
Project-URL: Homepage, https://github.com/sky-cloud/inet-api-client
Project-URL: Repository, https://github.com/sky-cloud/inet-api-client
Project-URL: Documentation, https://github.com/sky-cloud/inet-api-client/blob/main/README.md
Project-URL: Bug Reports, https://github.com/sky-cloud/inet-api-client/issues
Keywords: inet-api,sky-cloud,api,client,network,management,vlan,vpn
Classifier: Development Status :: 4 - Beta
Classifier: Intended Audience :: Developers
Classifier: License :: OSI Approved :: MIT License
Classifier: Operating System :: OS Independent
Classifier: Programming Language :: Python :: 3
Classifier: Programming Language :: Python :: 3.8
Classifier: Programming Language :: Python :: 3.9
Classifier: Programming Language :: Python :: 3.10
Classifier: Programming Language :: Python :: 3.11
Classifier: Topic :: Software Development :: Libraries :: Python Modules
Classifier: Topic :: Internet :: WWW/HTTP :: HTTP Servers
Classifier: Topic :: System :: Networking
Requires-Python: >=3.8
Requires-Dist: aiohttp>=3.8.0
Requires-Dist: pyjwt>=2.0.0
Requires-Dist: pycryptodome>=3.15.0
Provides-Extra: dev
Requires-Dist: pytest>=7.0.0; extra == "dev"
Requires-Dist: pytest-asyncio>=0.21.0; extra == "dev"
Requires-Dist: black>=22.0.0; extra == "dev"
Requires-Dist: flake8>=5.0.0; extra == "dev"
Requires-Dist: mypy>=1.0.0; extra == "dev"
Dynamic: author
Dynamic: home-page
Dynamic: requires-python
